MANIFEST.in
README.rst
setup.py
aliyun_python_sdk_ledgerdb.egg-info/PKG-INFO
aliyun_python_sdk_ledgerdb.egg-info/SOURCES.txt
aliyun_python_sdk_ledgerdb.egg-info/dependency_links.txt
aliyun_python_sdk_ledgerdb.egg-info/requires.txt
aliyun_python_sdk_ledgerdb.egg-info/top_level.txt
aliyunsdkledgerdb/__init__.py
aliyunsdkledgerdb/request/__init__.py
aliyunsdkledgerdb/request/v20191122/AcceptMemberRequest.py
aliyunsdkledgerdb/request/v20191122/CreateVpcEndpointRequest.py
aliyunsdkledgerdb/request/v20191122/DeleteLedgerRequest.py
aliyunsdkledgerdb/request/v20191122/DeleteMemberRequest.py
aliyunsdkledgerdb/request/v20191122/DeleteVpcEndpointRequest.py
aliyunsdkledgerdb/request/v20191122/DescribeLedgerRequest.py
aliyunsdkledgerdb/request/v20191122/DescribeLedgersRequest.py
aliyunsdkledgerdb/request/v20191122/DescribeRegionsRequest.py
aliyunsdkledgerdb/request/v20191122/DisableMemberRequest.py
aliyunsdkledgerdb/request/v20191122/EnableMemberRequest.py
aliyunsdkledgerdb/request/v20191122/GetJournalRequest.py
aliyunsdkledgerdb/request/v20191122/GetMemberRequest.py
aliyunsdkledgerdb/request/v20191122/InviteMembersRequest.py
aliyunsdkledgerdb/request/v20191122/ListJournalsRequest.py
aliyunsdkledgerdb/request/v20191122/ListMembersRequest.py
aliyunsdkledgerdb/request/v20191122/ListTimeAnchorsRequest.py
aliyunsdkledgerdb/request/v20191122/ListVpcEndpointsRequest.py
aliyunsdkledgerdb/request/v20191122/ModifyLedgerAttributeRequest.py
aliyunsdkledgerdb/request/v20191122/ModifyMemberACLsRequest.py
aliyunsdkledgerdb/request/v20191122/ModifyMemberKeyRequest.py
aliyunsdkledgerdb/request/v20191122/__init__.py